{"flutter_mac下环境搭建.md":"5bb0bccf","index.md":"31632c83","angular_指令.md":"e8bbb51b","angular_快速入门.md":"508fe2eb","node_node 学习笔记 http -- http.clientrequest.md":"1fa14318","node_node使用问题.md":"bf4217a1","angular_index.md":"6b02592f","mysql_sql-serve使用.md":"dfca3264","node_index.md":"de8b98a4","node_rest风格的api.md":"cda59e7f","node_centos云主机安装node.md":"84ea34b3","node_node学习笔记---全局对象.md":"92e8bb7f","latest_index.md":"6a100448","node_how-to-use-pnpm.md":"8affa20a","readme.md":"38357d33","mysql_mongodb.md":"fd8fcc94","node_mongoose模块学习.md":"6857ff3e","angular_组件.md":"10ee600c","mysql_index.md":"87c91cd5","node_node常见的编码规范.md":"ca5fcfce","others_linux_ubuntu_入门使用.md":"abe48261","others_linux_centos_yum的使用.md":"c53020b8","node_node学习笔记http -- response.md":"41047a87","node_node环境变量.md":"10bc1bb3","others_linux_centos_问题记录.md":"af373a6a","others_dev-tool_choco包管理器.md":"b2ffb77d","node_nvm使用.md":"4cfa519c","node_《node开发指南》学习笔记（一）--- node 简介.md":"dfb51597","node_如何在本地测试npm包.md":"cee06f3e","others_dev-tool_eslint.md":"a11d1833","node_npm使用问题.md":"3e2cac55","others_linux_centos_入门使用.md":"05ddecc2","node_node学习笔记util模块.md":"9cccca80","node_yarn使用.md":"9bf9a9ab","node_node学习笔记之path模块.md":"aa6d2b62","others_linux_centos_docker.md":"39ec1b7a","node_npm脚本使用.md":"26f2bbfa","node_npm语义化版本.md":"278ab86c","others_dev-tool_git.md":"7edf50ee","node_node学习笔记之querystring和url.md":"fbf104ad","others_dev-tool_git提交规范.md":"659a7c9c","node_node中的es6.md":"fbde5f92","others_functional-programming_尾递归.md":"468aa8c7","mysql_note.md":"89f8ac35","node_npm使用.md":"4b8b4d49","others_functional-programming_函子.md":"10d1f2e7","node_node学习笔记http模块之http.server.md":"0fe46b5c","node_npm源管理的方式.md":"12f785d7","others_functional-programming_数据不可变.md":"1024068f","others_functional-programming_项目中使用函数式编程改善代码.md":"d544c141","node_node路由.md":"1091a166","others_mac_index.md":"543bd755","others_mac_item2.md":"32a5d628","others_dev-tool_jsconfig文件.md":"fba38b1c","others_ts_使用技巧.md":"0d62343c","others_ts_如可快速新建一个项目.md":"5f9f3e49","others_vitepress_index.md":"5579a3ad","packages_index.md":"e5a66b45","react_compound-component.md":"70730075","react_control-props.md":"49fc045a","others_functional-programming_index.md":"6e712c53","react_如何写好条件渲染.md":"b48c991c","scheme_环境搭建.md":"3b6afea6","science_index.md":"cad97f45","vue2_commonjs和es6模块在vue中混用.md":"000cac84","vue2_index.md":"ca3037db","react_render-props.md":"c9cd95b5","science_中医与巫术.md":"d1b29315","others_mac_mac使用记录.md":"52d4a7ab","node_mongodb数据库基本使用.md":"637e1c85","vue2_test-component-event.md":"669e9233","node_node操作数据库.md":"44500bd9","others_dev-tool_index.md":"af134360","node_node学习笔记http模块之request.md":"20f31651","others_ts_index.md":"3c6b6432","others_functional-programming_函数式编程概述.md":"5ec9a6c7","science_中医的玄学之路.md":"13a274bc","others_dev-tool_我的git命令别名.md":"ab2a5381","others_functional-programming_函数计算得到函数.md":"0b548ead","others_dev-tool_vscode配置.md":"fae42b09","react_index.md":"bdd4eacf","others_dev-tool_vscode.md":"a5caebc3","node_what-is-npmrc.md":"482242ee","packages_dayjs使用.md":"19fbc168","react_react简介.md":"b0cf6de2","react_jsx语法.md":"1c998ec3","web_js_stencil组件.md":"d6546337","webpack_rollup基础使用.md":"031fcad2","web_js_封装axios.md":"2e0b8cd0","web-gis_地图库学习要点.md":"7f53e815","web_js_常见面试题.md":"9b5bd57a","web_js_jest-get-started.md":"5d010303","web_js_手写绑定函数.md":"352ce13a","others_dev-tool_win-software-list.md":"6da0f442","vue2_some-issues.md":"47d573fc","vue2_vue-pro-deploy-gh-pages.md":"983a1c09","node_node核心模块学习之buffer.md":"80c789e3","web_js_要不要写代码注释.md":"1af123dc","web_js_跨域请求.md":"c49da3c6","vue3_pinia使用教程一.md":"373b754d","web3_web3 《黑话词典》与演变史.md":"7b50ecf1","web3_index.md":"0569f00c","webpack_index.md":"ace48f1f","web_js_正则.md":"a5802b4f","webpack_如何使用gh-pages部署vue应用.md":"59174615","vue3_常用的tailwind类.md":"61a77e83","others_mac_youtube-dl.md":"dce9b38b","web_js_stencil简介.md":"bc7c69b1","vue2_render函数.md":"efaffeb4","react_intermediate.md":"2f0746d5","others_mac_终端使用.md":"2b033fe0","others_ts_tsconfig配置说明.md":"1a3f966c","web_js_jest-note-1.md":"8ed9ac5b","web_js_jest-setup-1.md":"0bc12c0c","vue3_vue项目使用apache部署解决404问题.md":"f581f6c9","vue3_一些杂问题.md":"9780b768","web_js_js常见面试题.md":"4be9d817","web_js_js性能技巧.md":"6fcd7eba","web_js_js技巧.md":"50d8d667","web_js_js风格编码风格.md":"7e1a85fd","vue2_test-better-to-organize-code.md":"30bd21e2","vue2_test-vue-intro.md":"947d26e2","vue3_如何监听组件生命周期钩子事件.md":"fc8facf2","web-gis_ol-1-map-init.md":"faaca8e3","vue3_技巧.md":"4f152c70","web-gis_index.md":"c2ff868a","vue3_生产级别的vue.md":"ec5017c8","vue3_监听生命周期钩子.md":"3ef665bf","web-gis_leaflet-map-init.md":"60a8ecc5","web-gis_leaflet克里金插值.md":"ec2a0be9","web-gis_leaflet地图放大镜.md":"306654ad","vue2_test-componet-output.md":"35cfca52","web-gis_leaflet整合高德地图.md":"77bfce91","vue2_test-snapshot.md":"c4d48e2f","web-gis_leaflet点聚合.md":"a8341bdf","vue2_test-component-method.md":"2f60772c","web-gis_leaflet要素编辑.md":"89f2ea40","vue3_组件设计之render-prop.md":"113a0f90","web-gis_ol-0.md":"8b520360","vue3_组件设计之分离公共行为.md":"f940068b","vue3_项目总结.md":"dc6b1e88","web-gis_ol-control.md":"b19c1f34","others_dev-tool_xshell使用.md":"7b3661aa","node_node学习笔记之commonjs规范.md":"e4bf5f8e","node_node学习笔记之events模块.md":"0d127058","vue2_vue-组件封装.md":"c65ad702","vue2_vue2响应式系统核心原理实现.md":"5159f1e4","vue2_vueconfig配置.md":"81d95808","vue2_vue路由基础.md":"ac4ac7ef","vue2_如何使用render函数封装高扩展的组件.md":"ada32e79","vue2_如何更好的管理公共组件.md":"0eef8913","vue2_常见面试题.md":"bbcc1557","webpack_模块联邦实现微前端.md":"0f80af9f","react_router路由.md":"13765c68","web_js_js基础重温.md":"6ed86d96","vue2_vue-状态管理（三）.md":"512ee221","vue3_flask 配置跨域.md":"6dc634f0","vue3_index.md":"4496ba1c","others_ts_jsdoc代替typescript语法.md":"249083e2","others_dev-tool_最常用的prettier配置.md":"5c8324e5","others_mac_美化终端.md":"6cc03623","web_js_箭头函数和普通函数的区别.md":"86121f1f","web-gis_leaflet-layer.md":"bac9e918","vue3_组件间通信.md":"1a172558","vue3_除了ref和reactive还有哪些函数声明响应式数据.md":"4f14cba3","web_js_jest-mock.md":"19a681b7","vue2_vue-状态管理（一）.md":"8f358025","vue3_指令.md":"a3a25955","vue2_test-vue-summary.md":"605e2e99","vue2_vue-状态管理（二）.md":"6708c705","web_js_jest-setup-2.md":"b7d517c9","react_react-basic.md":"78ff8497","web-gis_ol-data-source.md":"c5964d90","vue3_element使用总结.md":"3662f75c","vue2_test-vuex.md":"b28e8a90","web-gis_ol-graph-draw.md":"e0f333f8","web-gis_other-question.md":"4c6d04bc","vue3_组件设计之受控组件.md":"1552e6c6","web-gis_leaflet-get-started.md":"c88d6e9b","web-gis_webgis学习笔记.md":"1659d6fe","web-gis_leaflet-label冲突检测.md":"622a931c","others_mac_homebrew使用.md":"66acf16a","web_js_null和undefined的区别.md":"83f06849","vue2_vue路由进阶.md":"05499c6d","vue3_render函数.md":"e84edea2","vue2_函数式组件.md":"5b3d6f11","vue3_vue3-watch-best-practice.md":"593892e3","web_js_the-art-of-readable-code.md":"d7b33e19","vue2_如何优雅地注册全局组件.md":"fba3a4f2","web_css_css性能.md":"3dcf6170","web-gis_地理数据格式.md":"7986dbc1","web_css_css书写规范.md":"f331f11b","web_css_css语法检查.md":"a03174e0","web_css_less基础.md":"10f478df","web_css_常见布局.md":"9e7e9b88","web_html_readme.md":"0fd97d2e","web_js_abortcontroller使用.md":"dc831094","web_html_移动端布局.md":"73f59c56","web_js_mime-type.md":"ac87e92c","web_js_how-select-teck-stack.md":"e29abd95","vue3_vue代码优化方案.md":"1f820682","web_js_index.md":"3e5ec126","web_js_http-content-disposition.md":"c0ea186b","vue3_vue3组件测试.md":"bc1d6927","vue3_vue中的样式.md":"f055f25f","vue3_vue3获取ref.md":"7129832f","vue3_如何检测一个元素是否在视窗中.md":"3322028d","vue3_如何在组件上使用v-model.md":"e0874472","vue3_tailwind简介.md":"637ece4a","vue3_vue3开启jsx.md":"bf755bda","vue3_vite自动导入组件和函数配置.md":"97a0ebd9"}
