{"readme.md":"a0bfd344","node_index.md":"8e3bd23f","angular_组件.md":"c5e6defe","node_node 学习笔记 http -- http.clientrequest.md":"7df90cb9","node_node学习笔记http -- response.md":"36f75a9d","mysql_mongodb.md":"eaee1e60","node_node学习笔记之events模块.md":"fe06f529","node_rest风格的api.md":"e057af15","node_node使用问题.md":"65a987ce","index.md":"5abe8544","mysql_sql-serve使用.md":"efe6d05a","node_node操作数据库.md":"5786251f","node_node学习笔记之querystring和url.md":"e272f7a8","mysql_index.md":"b3ed5e30","node_node学习笔记http模块之request.md":"38377c8d","node_node核心模块学习之buffer.md":"dfbc8def","node_npm脚本使用.md":"715f889b","flutter_mac下环境搭建.md":"ea120089","angular_指令.md":"8b4cd71f","node_nvm使用.md":"33d133ad","node_centos云主机安装node.md":"b31f8c7e","node_如何在本地测试npm包.md":"c995f0cf","node_what-is-npmrc.md":"ce0a87c5","node_node学习笔记之path模块.md":"b4660120","node_mongoose模块学习.md":"42b49c14","node_ci-vs-i.md":"79889326","node_yarn使用.md":"13fc175d","others_dev-tool_git.md":"de2b45c9","latest_index.md":"703c2efa","node_node学习笔记http模块之http.server.md":"06b8338a","node_node环境变量.md":"f3350e65","node_node学习笔记util模块.md":"e4f3177e","node_《node开发指南》学习笔记（一）--- node 简介.md":"1e19beec","node_how-to-use-pnpm.md":"00d2ad71","others_linux_centos_yum的使用.md":"e841dce3","others_linux_centos_入门使用.md":"4e8e88ee","others_linux_centos_问题记录.md":"da4494b2","node_node学习笔记之commonjs规范.md":"140d73b3","others_dev-tool_choco包管理器.md":"dec21b3e","others_dev-tool_eslint.md":"504478ae","node_node中的es6.md":"43ba91b3","node_npm使用.md":"1307a036","others_linux_ubuntu_入门使用.md":"0f75ea91","mysql_note.md":"60d562ca","node_mongodb数据库基本使用.md":"bc5e5e1a","node_npm语义化版本.md":"9986bf1f","node_node常见的编码规范.md":"559a913f","others_dev-tool_jsconfig文件.md":"7b4e74c6","node_npm源管理的方式.md":"63d61a56","react_jsx语法.md":"55b0bcaa","node_node学习笔记---全局对象.md":"c83feffa","others_dev-tool_vscode配置.md":"8a8fce43","others_mac_youtube-dl.md":"a779b4ce","web-gis_leaflet点聚合.md":"7e83ea47","vue3_flask 配置跨域.md":"760dc21c","others_functional-programming_尾递归.md":"8594ca76","others_ts_使用技巧.md":"134de315","others_ts_index.md":"3c67f235","others_functional-programming_函子.md":"e5b1f931","others_mac_终端使用.md":"a17d6a7f","others_functional-programming_数据不可变.md":"3266b137","others_ts_tsconfig配置说明.md":"507274a7","vue2_vueconfig配置.md":"8f8db514","vue2_index.md":"126f7cd6","others_dev-tool_index.md":"1b2bfd0d","others_mac_mac使用记录.md":"5dc7d40c","others_dev-tool_git提交规范.md":"9a2371b8","web-gis_ol-graph-draw.md":"56953a39","others_dev-tool_win-software-list.md":"41fb9610","others_dev-tool_最常用的prettier配置.md":"61de48b2","packages_dayjs使用.md":"af638b83","others_functional-programming_index.md":"3580d78c","others_dev-tool_vscode.md":"5bc06335","angular_快速入门.md":"c654e21b","others_linux_centos_docker.md":"c28d7d99","vue3_组件设计之分离公共行为.md":"53f09435","vue3_render函数.md":"9787b907","others_dev-tool_我的git命令别名.md":"b9423b9b","angular_index.md":"291646ae","others_dev-tool_how-to-debug-in-vscode.md":"5faa0e01","others_dev-tool_xshell使用.md":"d85b200b","node_npm使用问题.md":"f81a4cc9","web_css_css书写规范.md":"50725596","react_index.md":"01f12cbf","packages_index.md":"a7147cde","others_mac_index.md":"36b390a9","others_mac_item2.md":"4415bd3d","vue3_常用的tailwind类.md":"70b99c21","others_mac_homebrew使用.md":"6b88dbdd","react_router路由.md":"1f8665ae","scheme_环境搭建.md":"27d35cee","science_index.md":"32715127","react_如何写好条件渲染.md":"1d5665f5","react_react简介.md":"e68b018f","science_中医与巫术.md":"c4bfe1ab","science_中医的玄学之路.md":"851e6a87","react_render-props.md":"2d0e64f8","vue2_commonjs和es6模块在vue中混用.md":"cd056bc9","react_intermediate.md":"8d49f80e","react_react-basic.md":"bd6f5b5d","web_js_手写绑定函数.md":"fd19ea18","web_js_两种阻止事件冒泡.md":"0eebe1ca","web_js_正则.md":"5af91cf6","web_js_useful-js-snippet.md":"fb226895","web_js_前端如何控制并发请求.md":"60c60493","web_js_箭头函数和普通函数的区别.md":"22695c3b","web3_web3 《黑话词典》与演变史.md":"9e704436","web_js_封装axios.md":"cb432b1f","vue2_test-vue-intro.md":"79d693b0","web3_index.md":"d9de8e6e","web_js_常见面试题.md":"740d099f","vue2_vue-pro-deploy-gh-pages.md":"68e7b370","webpack_index.md":"2ec350a5","vue2_vue-状态管理（一）.md":"e767d099","vue2_test-snapshot.md":"726036e3","web_js_要不要写代码注释.md":"84ebb67b","webpack_rollup基础使用.md":"2838b6b8","webpack_vite使用问题记录.md":"0d22cd82","webpack_如何使用gh-pages部署vue应用.md":"991de2ed","webpack_如何检查文件命名规范.md":"fba787ea","vue2_vue路由基础.md":"534af932","vue2_vue路由进阶.md":"e4db593c","vue2_函数式组件.md":"b4fc9e7c","vue2_如何优雅地注册全局组件.md":"7b81e5c2","vue2_如何使用render函数封装高扩展的组件.md":"2c6ddf3a","vue2_常见面试题.md":"b1671655","web-gis_leaflet要素编辑.md":"9ed90dbd","vue2_如何更好的管理公共组件.md":"f56df84e","others_functional-programming_项目中使用函数式编程改善代码.md":"79c82af1","vue3_element使用总结.md":"e950024e","others_mac_美化终端.md":"c2a57402","web-gis_index.md":"73d62405","vue3_vite自动导入组件和函数配置.md":"ce662d01","vue3_组件设计之render-prop.md":"ce8f5ad0","vue3_如何在组件上使用v-model.md":"a27e4c70","vue3_vue代码优化方案.md":"2ddb44ab","vue3_vue项目使用apache部署解决404问题.md":"45ffcdc2","vue3_弹窗封装.md":"58673792","react_control-props.md":"ae97a2ef","vue3_如何检测一个元素是否在视窗中.md":"5f29c6fa","vue3_技巧.md":"3a82f6fa","vue3_生产级别的vue.md":"232247b1","others_ts_jsdoc代替typescript语法.md":"1b40562b","others_ts_如可快速新建一个项目.md":"e97b8920","vue3_tailwind简介.md":"4c62eab1","vue3_指令.md":"273c726b","vue3_一些杂问题.md":"fb5950b5","packages_说说日期格式.md":"d4f31116","others_functional-programming_函数计算得到函数.md":"19e2137f","vue3_index.md":"538cca27","others_functional-programming_技术债务和工程文化.md":"f3d26ddd","web-gis_ol-0.md":"d71a3f02","web_js_jest-note-1.md":"2555f206","vue3_vue3获取ref.md":"e73b5388","web_js_jest-setup-1.md":"8f0efab2","vue3_vue中的样式.md":"dc019130","web_css_selector-specificity.md":"411a73d6","node_node路由.md":"d4eca2d2","web-gis_ol-data-source.md":"b3fc6510","web-gis_other-question.md":"a62ac004","web-gis_webgis学习笔记.md":"7e52f331","web-gis_地图库学习要点.md":"629f19d1","web-gis_地图投影.md":"7d348b7d","web-gis_ol-1-map-init.md":"9e556af9","web_css_20个编写现代css的进阶技巧.md":"f4203158","vue2_render函数.md":"bf692a64","web-gis_地理数据格式.md":"dc425734","web_css_css性能.md":"6d65ce8b","vue3_组件设计之受控组件.md":"b9c64e00","web_css_less基础.md":"1e2c2531","web_css_layer-syntax.md":"43830f0b","web_css_tailwind和组件库样式冲突.md":"b561ada3","web_html_readme.md":"5974e482","vue3_vue3-watch-best-practice.md":"07942cd3","web_css_常见布局.md":"4b6fa5d9","web_html_移动端布局.md":"329844a3","web_js_abortcontroller使用.md":"7f0f9556","web_js_mime-type.md":"5a7faef2","vue3_pinia使用教程一.md":"26e5f523","web_js_bit-map-and-vertor-map.md":"4634701c","web_js_http-content-disposition.md":"aa8701c6","web_js_index.md":"9a819274","web_js_js风格编码风格.md":"77e0beb0","web_css_css语法检查.md":"cae4a2fc","web_js_how-select-teck-stack.md":"ec570adc","web_js_js技巧.md":"200ba23a","vue3_除了ref和reactive还有哪些函数声明响应式数据.md":"49c74361","web_js_js常见面试题.md":"fe6eba7e","others_vitepress_index.md":"58ef3e54","web_js_null和undefined的区别.md":"bb3f9e97","vue3_如何监听组件生命周期钩子事件.md":"a8b395f5","web_js_stencil组件.md":"31e14b54","vue3_vue3开启jsx.md":"9ec3df87","web_js_js性能技巧.md":"db8f667b","web_js_js基础重温.md":"b576bc6e","web_js_jest-setup-2.md":"614624a0","web_js_jest-get-started.md":"645b6ec3","react_compound-component.md":"949a6871","vue3_组件间通信.md":"b1878c78","others_functional-programming_函数式编程概述.md":"4c11d252","web-gis_leaflet-label冲突检测.md":"858b08a9","vue2_vue-状态管理（二）.md":"0107b926","web-gis_leaflet地图放大镜.md":"e551e612","vue2_some-issues.md":"238d7464","vue2_vue2响应式系统核心原理实现.md":"efb51ab3","web_js_jest-mock.md":"256c863d","vue2_vue2中如何动态渲染组件.md":"d3ced55e","vue2_test-component-method.md":"70304c68","web-gis_leaflet整合高德地图.md":"5afda351","vue2_vue-状态管理（三）.md":"2bf3e5d5","web-gis_leaflet-layer.md":"21a79b80","vue2_test-componet-output.md":"af4dcada","web-gis_leaflet克里金插值.md":"8d2240cb","web-gis_leaflet-map-init.md":"233be6c7","vue3_项目总结.md":"cec6b9cd","vue2_test-vue-summary.md":"fd6047e0","vue2_vue-组件封装.md":"aed99200","vue2_test-better-to-organize-code.md":"61792cf8","vue3_vue3组件测试.md":"413d8245","web_js_stencil简介.md":"0af4885e","vue2_test-component-event.md":"cb7b7161","vue2_test-vuex.md":"89d8a4b3","web-gis_leaflet-get-started.md":"d22ed35c","webpack_模块联邦实现微前端.md":"f5f6e525","web_js_跨域请求.md":"829ebe03","web_js_the-art-of-readable-code.md":"a95e26e8"}
