{"node_node学习笔记之path模块.md":"27ba4819","node_nvm使用.md":"60728fa0","readme.md":"bb6567d3","others_dev-tool_jsconfig文件.md":"59a12aaa","node_node环境变量.md":"05babf85","node_index.md":"94b898c3","others_functional-programming_函数式编程概述.md":"b61942f2","node_node 学习笔记 http -- http.clientrequest.md":"c96ec022","angular_指令.md":"3a0bd725","flutter_mac下环境搭建.md":"3e0ef069","others_functional-programming_数据不可变.md":"782ca4a9","node_mongodb数据库基本使用.md":"888a6be2","angular_index.md":"8945854b","mysql_note.md":"29e1e786","others_functional-programming_项目中使用函数式编程改善代码.md":"01f21017","others_mac_美化终端.md":"6075d1a3","others_mac_youtube-dl.md":"09a53de8","others_mac_item2.md":"fc1d47d0","others_ts_如可快速新建一个项目.md":"f5910a01","others_mac_mac使用记录.md":"53ff1798","others_ts_tsconfig配置说明.md":"4698e489","science_index.md":"9608ddf8","packages_index.md":"b4a70ebc","react_index.md":"c036532e","react_control-props.md":"a0a180fc","node_node使用问题.md":"a6ccd504","science_中医与巫术.md":"816a7d25","others_mac_homebrew使用.md":"4c7375da","vue2_vue-pro-deploy-gh-pages.md":"aea34e32","vue2_test-vue-intro.md":"e9adf36c","vue3_tailwind简介.md":"a674d56f","react_render-props.md":"6b681cc0","vue2_如何优雅地注册全局组件.md":"81dfcf54","web-gis_leaflet-layer.md":"273d4469","vue2_test-snapshot.md":"daedff45","node_node学习笔记之querystring和url.md":"39dad309","vue2_vueconfig配置.md":"648f93ff","vue3_如何在组件上使用v-model.md":"b62231de","node_node路由.md":"2d53feab","others_dev-tool_最常用的prettier配置.md":"cdaa6cf1","node_node学习笔记---全局对象.md":"6ca9ba64","angular_快速入门.md":"70825292","node_npm使用问题.md":"0a7c9a8e","others_functional-programming_index.md":"987ed1f2","node_npm源管理的方式.md":"5c62aad9","node_centos云主机安装node.md":"c6cf7bc8","node_node学习笔记http模块之http.server.md":"8f1d7524","node_npm脚本使用.md":"aca57b4a","index.md":"f1e6b2db","vue3_常用的tailwind类.md":"3aea3b0f","vue2_vue路由进阶.md":"37344275","others_dev-tool_choco包管理器.md":"f722c1ff","node_node学习笔记之events模块.md":"871ec860","node_yarn使用.md":"01a995ca","others_dev-tool_git.md":"c907a671","vue3_技巧.md":"38a1f9f0","others_dev-tool_index.md":"7221773e","node_node学习笔记http -- response.md":"3a9069d8","mysql_index.md":"483c6932","vue2_函数式组件.md":"5d3290e5","node_《node开发指南》学习笔记（一）--- node 简介.md":"f6aee145","node_如何在本地测试npm包.md":"5311b976","vue2_some-issues.md":"a331e053","others_linux_centos_问题记录.md":"9f726891","vue2_commonjs和es6模块在vue中混用.md":"6386e3db","node_node操作数据库.md":"f02eaa4f","angular_组件.md":"a9db1033","node_rest风格的api.md":"7d2b3515","scheme_环境搭建.md":"43ef6932","node_node核心模块学习之buffer.md":"b2139cd9","others_mac_终端使用.md":"2af3f9a2","others_ts_readme.md":"0a22efec","others_dev-tool_xshell使用.md":"78d9b42c","others_dev-tool_我的git命令别名.md":"5c56b628","web-gis_ol-1-map-init.md":"da677a2c","others_vitepress_index.md":"ef8caa74","web-gis_other-question.md":"5967b4a4","web-gis_ol-data-source.md":"aa5ea95a","web-gis_ol-graph-draw.md":"0e083fe5","latest_index.md":"22fbbbfc","node_node学习笔记之commonjs规范.md":"1a720db7","web-gis_ol-control.md":"7b5819b9","web_css_less基础.md":"4d82fd8e","web_css_常见布局.md":"726bfe59","web_html_readme.md":"9f23738b","web_html_移动端布局.md":"6c436b1a","web_js_index.md":"8cdde2bf","web-gis_leaflet要素编辑.md":"61aca540","web_css_css语法检查.md":"1423dc32","web-gis_ol-0.md":"79b50eb0","web_js_abortcontroller使用.md":"74fa34c3","web_js_mime-type.md":"f967bc50","web_js_how-select-teck-stack.md":"0aa95222","react_compound-component.md":"d2f31249","vue2_index.md":"d30b92d4","web_js_http-content-disposition.md":"25dd92b8","react_react-basic.md":"4b446566","web-gis_地图库学习要点.md":"a1000c01","web_css_css性能.md":"28fb88ec","web_css_css书写规范.md":"94883d69","node_node中的es6.md":"ef253256","others_dev-tool_vscode配置.md":"efd3d92d","node_mongoose模块学习.md":"baeda406","others_ts_使用技巧.md":"f2eee85a","react_router路由.md":"312f5997","react_jsx语法.md":"c9537b1d","react_如何写好条件渲染.md":"7608fe1b","others_dev-tool_win-software-list.md":"f7f8047c","science_中医的玄学之路.md":"e50ada50","vue3_element使用总结.md":"8c03994e","vue3_vue3开启jsx.md":"b6cf627a","vue3_flask 配置跨域.md":"f5bace89","vue2_vue-状态管理（一）.md":"a98866b5","vue2_vue-状态管理（三）.md":"836fc3b4","vue3_index.md":"433b7293","vue3_vue3-watch-best-practice.md":"c1970d49","vue3_组件间通信.md":"70138889","vue2_vue-状态管理（二）.md":"71493e23","vue3_除了ref和reactive还有哪些函数声明响应式数据.md":"be696a04","web-gis_leaflet克里金插值.md":"70b475c7","vue3_vue中的样式.md":"86732f08","vue3_vue3获取ref.md":"57cfc853","vue3_项目总结.md":"94a20acd","web-gis_index.md":"06f00683","vue3_vue项目使用apache部署解决404问题.md":"488131cf","vue2_vue-组件封装.md":"65aad281","vue3_组件设计之分离公共行为.md":"18893b99","vue3_vue代码优化方案.md":"262aa323","web-gis_leaflet-map-init.md":"055fd481","vue3_如何监听组件生命周期钩子事件.md":"3bf032e5","vue3_组件设计之render-prop.md":"9c415aa4","web-gis_leaflet点聚合.md":"502febe8","web-gis_leaflet整合高德地图.md":"6a5d10ff","others_functional-programming_尾递归.md":"e2cf911d","vue3_组件设计之受控组件.md":"61715af9","node_how-to-use-pnpm.md":"b078f12d","web-gis_leaflet地图放大镜.md":"72136eb4","others_dev-tool_vscode.md":"4b198e7d","react_intermediate.md":"5bf423ab","others_functional-programming_函子.md":"970ff1fb","mysql_sql-serve使用.md":"8b8d8e44","others_linux_centos_docker.md":"a548b28e","node_node常见的编码规范.md":"b16d949e","vue2_test-vue-summary.md":"907c962d","others_dev-tool_eslint.md":"90765436","others_mac_index.md":"e1071355","node_node学习笔记http模块之request.md":"abca3d43","others_linux_centos_yum的使用.md":"3a074426","vue3_如何检测一个元素是否在视窗中.md":"5799fdce","node_npm语义化版本.md":"e15681d1","vue2_render函数.md":"5664466a","mysql_mongodb.md":"dc5dd26f","others_linux_centos_入门使用.md":"def50141","node_npm使用.md":"002d751a","others_dev-tool_git提交规范.md":"37c01a0e","packages_dayjs使用.md":"c324136a","others_linux_ubuntu_入门使用.md":"fd812de2","webpack_index.md":"da7b4622","web_js_跨域请求.md":"5829579b","others_functional-programming_函数计算得到函数.md":"c89e639b","web_js_要不要写代码注释.md":"75312b6e","webpack_如何使用gh-pages部署vue应用.md":"94d0d99e","node_node学习笔记util模块.md":"3712d69f","react_react简介.md":"38fd526c","web_js_jest-get-started.md":"d6d1ecf8","web_js_jest-note-1.md":"edd729b8","web-gis_webgis学习笔记.md":"392a71f0","web_js_jest-setup-1.md":"2a60105f","web_js_js技巧.md":"db1d7714","web_js_js基础重温.md":"e75f6110","vue3_vite自动导入组件和函数配置.md":"af153a53","vue2_如何更好的管理公共组件.md":"f6d95cc9","web-gis_leaflet-label冲突检测.md":"02225cb8","vue3_监听生命周期钩子.md":"c7adf412","vue2_vue2响应式系统核心原理实现.md":"dd3201f7","vue3_一些杂问题.md":"0c6bc1ed","web-gis_leaflet-get-started.md":"2c930bb0","vue3_生产级别的vue.md":"48c48c16","vue2_vue路由基础.md":"3fa5911f","vue2_test-componet-output.md":"16a43ae8","vue2_test-vuex.md":"04b47876","web_js_js常见面试题.md":"070f19fc","vue3_指令.md":"4b329b9c","vue2_如何使用render函数封装高扩展的组件.md":"ada459cf","webpack_rollup基础使用.md":"dbf6f200","vue3_pinia使用教程一.md":"e5e22097","web_js_手写绑定函数.md":"d88d7610","web_js_null和undefined的区别.md":"b5e9e5f0","vue3_vue3组件测试.md":"d4b46963","web_js_正则.md":"f236eddd","web_js_箭头函数和普通函数的区别.md":"975eac51","web_js_js性能技巧.md":"ef4755ef","web_js_js风格编码风格.md":"c2149891","web_js_stencil简介.md":"4fdf045a","vue2_test-component-method.md":"b23aae0c","vue2_test-better-to-organize-code.md":"939ef663","vue2_test-component-event.md":"e970ba2b","web_js_stencil组件.md":"8b21f382","webpack_模块联邦实现微前端.md":"f861d64a","web_js_jest-mock.md":"55200408","vue3_render函数.md":"7d7f4eb4","web_js_jest-setup-2.md":"b9fa2920","web_js_封装axios.md":"1287f071","web_js_the-art-of-readable-code.md":"d59db9b3"}
